hashable_df/__init__.py
hashable_df-0.0.8.dist-info/LICENSE
hashable_df-0.0.8.dist-info/METADATA
hashable_df-0.0.8.dist-info/WHEEL
hashable_df-0.0.8.dist-info/top_level.txt
hashable_df-0.0.8.dist-info/RECORD
