Metadata-Version: 2.1
Name: hashable_df
Version: 0.0.8
Summary: Makes unhashable values in a pandas DataFrame hashable
Author-email: "NAGY, Attila" <nagy.attila@gmail.com>
Project-URL: Homepage, https://github.com/bra-fsn/hashable_df
Project-URL: Source, https://github.com/bra-fsn/hashable_df
Classifier: Programming Language :: Python
Classifier: License :: OSI Approved :: MIT License
Classifier: Operating System :: OS Independent
License-File: LICENSE
Requires-Dist: autohash
Requires-Dist: numpy
